{"nodes": [{"id": "backend_app_routers_uploads_py", "label": "uploads.py", "file_type": "code", "source_file": "backend/app/routers/uploads.py", "source_location": "L1"}, {"id": "uploads_validate_api_key", "label": "_validate_api_key()", "file_type": "code", "source_file": "backend/app/routers/uploads.py", "source_location": "L17"}, {"id": "uploads_save_file", "label": "_save_file()", "file_type": "code", "source_file": "backend/app/routers/uploads.py", "source_location": "L27"}, {"id": "uploads_upload_snapshot", "label": "upload_snapshot()", "file_type": "code", "source_file": "backend/app/routers/uploads.py", "source_location": "L40"}, {"id": "uploads_upload_clip", "label": "upload_clip()", "file_type": "code", "source_file": "backend/app/routers/uploads.py", "source_location": "L51"}], "edges": [{"source": "backend_app_routers_uploads_py", "target": "os", "relation": "imports", "confidence": "EXTRACTED", "source_file": "backend/app/routers/uploads.py", "source_location": "L1", "weight": 1.0}, {"source": "backend_app_routers_uploads_py", "target": "uuid", "relation": "imports", "confidence": "EXTRACTED", "source_file": "backend/app/routers/uploads.py", "source_location": "L2", "weight": 1.0}, {"source": "backend_app_routers_uploads_py", "target": "datetime", "relation": "imports_from", "confidence": "EXTRACTED", "source_file": "backend/app/routers/uploads.py", "source_location": "L3", "weight": 1.0}, {"source": "backend_app_routers_uploads_py", "target": "fastapi", "relation": "imports_from", "confidence": "EXTRACTED", "source_file": "backend/app/routers/uploads.py", "source_location": "L5", "weight": 1.0}, {"source": "backend_app_routers_uploads_py", "target": "sqlalchemy_orm", "relation": "imports_from", "confidence": "EXTRACTED", "source_file": "backend/app/routers/uploads.py", "source_location": "L6", "weight": 1.0}, {"source": "backend_app_routers_uploads_py", "target": "app_config", "relation": "imports_from", "confidence": "EXTRACTED", "source_file": "backend/app/routers/uploads.py", "source_location": "L8", "weight": 1.0}, {"source": "backend_app_routers_uploads_py", "target": "app_database", "relation": "imports_from", "confidence": "EXTRACTED", "source_file": "backend/app/routers/uploads.py", "source_location": "L9", "weight": 1.0}, {"source": "backend_app_routers_uploads_py", "target": "app_models_camera", "relation": "imports_from", "confidence": "EXTRACTED", "source_file": "backend/app/routers/uploads.py", "source_location": "L10", "weight": 1.0}, {"source": "backend_app_routers_uploads_py", "target": "uploads_validate_api_key", "relation": "contains", "confidence": "EXTRACTED", "source_file": "backend/app/routers/uploads.py", "source_location": "L17", "weight": 1.0}, {"source": "backend_app_routers_uploads_py", "target": "uploads_save_file", "relation": "contains", "confidence": "EXTRACTED", "source_file": "backend/app/routers/uploads.py", "source_location": "L27", "weight": 1.0}, {"source": "backend_app_routers_uploads_py", "target": "uploads_upload_snapshot", "relation": "contains", "confidence": "EXTRACTED", "source_file": "backend/app/routers/uploads.py", "source_location": "L40", "weight": 1.0}, {"source": "backend_app_routers_uploads_py", "target": "uploads_upload_clip", "relation": "contains", "confidence": "EXTRACTED", "source_file": "backend/app/routers/uploads.py", "source_location": "L51", "weight": 1.0}, {"source": "uploads_upload_snapshot", "target": "uploads_validate_api_key", "relation": "calls", "confidence": "EXTRACTED", "source_file": "backend/app/routers/uploads.py", "source_location": "L45", "weight": 1.0}, {"source": "uploads_upload_snapshot", "target": "uploads_save_file", "relation": "calls", "confidence": "EXTRACTED", "source_file": "backend/app/routers/uploads.py", "source_location": "L46", "weight": 1.0}, {"source": "uploads_upload_clip", "target": "uploads_validate_api_key", "relation": "calls", "confidence": "EXTRACTED", "source_file": "backend/app/routers/uploads.py", "source_location": "L56", "weight": 1.0}, {"source": "uploads_upload_clip", "target": "uploads_save_file", "relation": "calls", "confidence": "EXTRACTED", "source_file": "backend/app/routers/uploads.py", "source_location": "L57", "weight": 1.0}], "raw_calls": [{"caller_nid": "uploads_validate_api_key", "callee": "first", "source_file": "backend/app/routers/uploads.py", "source_location": "L21"}, {"caller_nid": "uploads_validate_api_key", "callee": "filter", "source_file": "backend/app/routers/uploads.py", "source_location": "L21"}, {"caller_nid": "uploads_validate_api_key", "callee": "query", "source_file": "backend/app/routers/uploads.py", "source_location": "L21"}, {"caller_nid": "uploads_validate_api_key", "callee": "HTTPException", "source_file": "backend/app/routers/uploads.py", "source_location": "L24"}, {"caller_nid": "uploads_save_file", "callee": "join", "source_file": "backend/app/routers/uploads.py", "source_location": "L28"}, {"caller_nid": "uploads_save_file", "callee": "makedirs", "source_file": "backend/app/routers/uploads.py", "source_location": "L29"}, {"caller_nid": "uploads_save_file", "callee": "splitext", "source_file": "backend/app/routers/uploads.py", "source_location": "L30"}, {"caller_nid": "uploads_save_file", "callee": "strftime", "source_file": "backend/app/routers/uploads.py", "source_location": "L31"}, {"caller_nid": "uploads_save_file", "callee": "now", "source_file": "backend/app/routers/uploads.py", "source_location": "L31"}, {"caller_nid": "uploads_save_file", "callee": "uuid4", "source_file": "backend/app/routers/uploads.py", "source_location": "L31"}, {"caller_nid": "uploads_save_file", "callee": "join", "source_file": "backend/app/routers/uploads.py", "source_location": "L32"}, {"caller_nid": "uploads_save_file", "callee": "open", "source_file": "backend/app/routers/uploads.py", "source_location": "L33"}, {"caller_nid": "uploads_save_file", "callee": "read", "source_file": "backend/app/routers/uploads.py", "source_location": "L34"}, {"caller_nid": "uploads_save_file", "callee": "write", "source_file": "backend/app/routers/uploads.py", "source_location": "L35"}]}